<?xml version="1.0" ?>
<annotation>
<folder>test</folder>
<filename>043_1_0017_1_j.png</filename>
<path>C:\Users\Administrator\Desktop\test\043_1_0017_1_j.png</path>
<source>
    <database>Unknown</database>
</source>
<size>
    <width>165</width>
    <height>175</height>
    <depth>3</depth>
</size>

<segmented>0</segmented>
    <object>
    <name>6</name>
    <pose>Unspecified</pose>
    <truncated>0</truncated>
    <difficult>0</difficult>
    <bndbox>
        <xmin>25</xmin>
        <ymin>39</ymin>
        <xmax>136</xmax>
        <ymax>131</ymax>
    </bndbox>
</object>
</annotation>
