<annotation>
	<folder>resized_1</folder>
	<filename>sign_256.jpg</filename>
	<path>C:\Users\lenovo\Desktop\resized_1\sign_256.jpg</path>
	<source>
		<database>Unknown</database>
	</source>
	<size>
		<width>640</width>
		<height>640</height>
		<depth>3</depth>
	</size>
	<segmented>0</segmented>
	<object>
		<name>crosswalk</name>
		<pose>Unspecified</pose>
		<truncated>0</truncated>
		<difficult>0</difficult>
		<bndbox>
			<xmin>228</xmin>
			<ymin>332</ymin>
			<xmax>281</xmax>
			<ymax>391</ymax>
		</bndbox>
	</object>
</annotation>
