<annotation>
	<folder>resized_2</folder>
	<filename>sign_329.jpg</filename>
	<path>C:\Users\lyc\Desktop\windows_v1.5.2\resized_2\sign_329.jpg</path>
	<source>
		<database>Unknown</database>
	</source>
	<size>
		<width>640</width>
		<height>640</height>
		<depth>3</depth>
	</size>
	<segmented>0</segmented>
	<object>
		<name>stop</name>
		<pose>Unspecified</pose>
		<truncated>0</truncated>
		<difficult>0</difficult>
		<bndbox>
			<xmin>71</xmin>
			<ymin>324</ymin>
			<xmax>124</xmax>
			<ymax>375</ymax>
		</bndbox>
	</object>
</annotation>
